dagster_feray/__init__.py
dagster_feray/calculator.py
dagster_feray/py.typed
dagster_feray-1.0.0.dist-info/WHEEL
dagster_feray-1.0.0.dist-info/METADATA
dagster_feray-1.0.0.dist-info/RECORD
