Metadata-Version: 2.3
Name: dagster-feray
Version: 1.0.0
Summary: dagster integration for feRay
Keywords: dagster,workflow-orchestration,ray,feray
Author: danielgafni, geoheil
Author-email: danielgafni <danielgafni16@gmail.com>, geoheil <georg.kf.heiler@gmail.com>
License: Apache-2.0
Classifier: Development Status :: 4 - Beta
Classifier: Intended Audience :: Developers
Classifier: License :: OSI Approved :: Apache Software License
Classifier: Operating System :: OS Independent
Classifier: Programming Language :: Python :: 3
Classifier: Programming Language :: Python :: 3.12
Classifier: Topic :: System :: Distributed Computing
Classifier: Topic :: Software Development :: Libraries :: Python Modules
Requires-Dist: feray
Requires-Dist: dagster>=1.11
Requires-Python: >=3.12
Project-URL: Bug Reports, https://github.com/feray-org/issues
Project-URL: Documentation, https://github.com/feray-org/docs/dagster
Project-URL: Homepage, https://github.com/feray-org/
Project-URL: Repository, https://github.com/feray-org
